Metadata-Version: 2.4
Name: wagtail_content_import
Version: 0.12.2
Summary: A module for Wagtail that provides functionality for importing page content from third-party sources.
Home-page: https://github.com/torchbox/wagtail-content-import
Author: Samir Shah, Jacob Topp-Mugglestone, Karl Hobley, Matthew Westcott
Author-email: jacobtm@torchbox.com
License: BSD
Classifier: Development Status :: 3 - Alpha
Classifier: Environment :: Web Environment
Classifier: Intended Audience :: Developers
Classifier: License :: OSI Approved :: BSD License
Classifier: Operating System :: OS Independent
Classifier: Programming Language :: Python
Classifier: Programming Language :: Python :: 3
Classifier: Programming Language :: Python :: 3.8
Classifier: Programming Language :: Python :: 3.9
Classifier: Programming Language :: Python :: 3.10
Classifier: Programming Language :: Python :: 3.11
Classifier: Programming Language :: Python :: 3.12
Classifier: Framework :: Django
Classifier: Framework :: Django :: 3.2
Classifier: Framework :: Django :: 4.1
Classifier: Framework :: Django :: 4.2
Classifier: Framework :: Django :: 5.0
Classifier: Framework :: Wagtail
Classifier: Framework :: Wagtail :: 4
Classifier: Framework :: Wagtail :: 5
Classifier: Framework :: Wagtail :: 6
Classifier: Topic :: Internet :: WWW/HTTP :: Site Management
License-File: LICENSE
Requires-Dist: wagtail>=4.1
Requires-Dist: python-docx>=0.8.10
Provides-Extra: testing
Requires-Dist: mock>=1.0.0; extra == "testing"
Requires-Dist: coverage>=3.7.0; extra == "testing"
Requires-Dist: flake8>=2.2.0; extra == "testing"
Requires-Dist: tox==3.9.0; extra == "testing"
Requires-Dist: dj-database-url==0.5.0; extra == "testing"
Dynamic: author
Dynamic: author-email
Dynamic: classifier
Dynamic: description
Dynamic: description-content-type
Dynamic: home-page
Dynamic: license
Dynamic: license-file
Dynamic: provides-extra
Dynamic: requires-dist
Dynamic: summary
